MANIFEST.in
README.md
requirements.txt
setup.py
pubrunner/__init__.py
pubrunner/command_line.py
pubrunner/convert.py
pubrunner/convertBioCToTSV.py
pubrunner/gather_pmids.py
pubrunner/getresource.py
pubrunner/globalsettings.py
pubrunner/pubmed_hash.py
pubrunner/pubrun.py
pubrunner/pubrunner.settings.default.yml
pubrunner/snakemake.py
pubrunner/upload.py
pubrunner.egg-info/PKG-INFO
pubrunner.egg-info/SOURCES.txt
pubrunner.egg-info/dependency_links.txt
pubrunner.egg-info/entry_points.txt
pubrunner.egg-info/not-zip-safe
pubrunner.egg-info/requires.txt
pubrunner.egg-info/top_level.txt
pubrunner/Snakefiles/Convert.py
pubrunner/Snakefiles/PubmedHashes.py
pubrunner/Snakefiles/Run.py
pubrunner/resources/DISEASE_ONTOLOGY.yml
pubrunner/resources/FOODON.yml
pubrunner/resources/METATHESAURUS_EMPTY.yml
pubrunner/resources/NCBI_GENE.yml
pubrunner/resources/NCBI_GENE_TEST.yml
pubrunner/resources/PMCAMC.yml
pubrunner/resources/PMCOA.yml
pubrunner/resources/PMCOA_TWOJOURNALS.yml
pubrunner/resources/PUBCHEM.yml
pubrunner/resources/PUBMED.yml
pubrunner/resources/PUBMED_TWOFILES.yml