Metadata-Version: 2.1
Name: pubrunner
Version: 0.5.3
Summary: A framework to rerun text mining tools on the latest publications
Home-page: http://github.com/jakelever/pubrunner
Author: Jake Lever
Author-email: jake.lever@gmail.com
License: MIT
Platform: UNKNOWN
Classifier: Intended Audience :: Developers
Classifier: Intended Audience :: Education
Classifier: Intended Audience :: Information Technology
Classifier: Intended Audience :: Science/Research
Classifier: License :: OSI Approved :: MIT License
Classifier: Operating System :: Unix
Classifier: Programming Language :: Python :: 3.6
Classifier: Topic :: Scientific/Engineering
